Metadata-Version: 2.1
Name: pyfrechet
Version: 0.1.12
Summary: Frechet Distance Python Library
Home-page: https://github.com/compgeomTU/frechetForCurves
Author: Will Rodman
Author-email: wrodman@tulane.edu
License: MIT
Download-URL: https://github.com/compgeomTU/frechetForCurves/archive/refs/tags/0.1.8.tar.gz
Platform: UNKNOWN
Classifier: Development Status :: 4 - Beta
Classifier: License :: OSI Approved :: MIT License
Classifier: Programming Language :: Python :: 3.9
License-File: LICENSE
